LICENSE
MANIFEST.in
README.md
setup.py
nautobot_ui_plugin/__init__.py
nautobot_ui_plugin/admin.py
nautobot_ui_plugin/filters.py
nautobot_ui_plugin/forms.py
nautobot_ui_plugin/models.py
nautobot_ui_plugin/navigation.py
nautobot_ui_plugin/template_content.py
nautobot_ui_plugin/urls.py
nautobot_ui_plugin/views.py
nautobot_ui_plugin.egg-info/PKG-INFO
nautobot_ui_plugin.egg-info/SOURCES.txt
nautobot_ui_plugin.egg-info/dependency_links.txt
nautobot_ui_plugin.egg-info/requires.txt
nautobot_ui_plugin.egg-info/top_level.txt
nautobot_ui_plugin/api/__init__.py
nautobot_ui_plugin/api/serializers.py
nautobot_ui_plugin/api/urls.py
nautobot_ui_plugin/api/views.py
nautobot_ui_plugin/migrations/0001_initial.py
nautobot_ui_plugin/migrations/__init__.py
nautobot_ui_plugin/static/nautobot_ui_plugin/bootstrap.bundle.min.js
nautobot_ui_plugin/static/nautobot_ui_plugin/bootstrap.min.css
nautobot_ui_plugin/static/nautobot_ui_plugin/button_utils.js
nautobot_ui_plugin/static/nautobot_ui_plugin/next_app.js
nautobot_ui_plugin/static/nautobot_ui_plugin/img/dead_node.png
nautobot_ui_plugin/static/nautobot_ui_plugin/jquery/jquery-3.5.1.min.js
nautobot_ui_plugin/static/nautobot_ui_plugin/jquery-ui-1.12.1/jquery-ui.min.js
nautobot_ui_plugin/static/nautobot_ui_plugin/next_sources/LICENSE.txt
nautobot_ui_plugin/static/nautobot_ui_plugin/next_sources/css/next.css
nautobot_ui_plugin/static/nautobot_ui_plugin/next_sources/doc/api.js
nautobot_ui_plugin/static/nautobot_ui_plugin/next_sources/doc/data.json
nautobot_ui_plugin/static/nautobot_ui_plugin/next_sources/doc/index.html
nautobot_ui_plugin/static/nautobot_ui_plugin/next_sources/doc/assets/favicon.ico
nautobot_ui_plugin/static/nautobot_ui_plugin/next_sources/doc/assets/index.html
nautobot_ui_plugin/static/nautobot_ui_plugin/next_sources/doc/assets/css/external-small.png
nautobot_ui_plugin/static/nautobot_ui_plugin/next_sources/doc/assets/css/logo.png
nautobot_ui_plugin/static/nautobot_ui_plugin/next_sources/doc/assets/css/main.css
nautobot_ui_plugin/static/nautobot_ui_plugin/next_sources/doc/assets/img/spinner.gif
nautobot_ui_plugin/static/nautobot_ui_plugin/next_sources/doc/assets/js/api-filter.js
