Metadata-Version: 2.1
Name: nautobot_ui_plugin
Version: 1.0.0
Summary: A topology visualization plugin for Nautobot powered by NextUI Toolkit.
Home-page: https://gitlab-ce.gwdg.de/gwdg-netz/nautobot-plugins/nautobot-ui-plugin/
Author: Gesellschaft für wissenschaftliche Datenverarbeitung mbH Göttingen
Author-email: netzadmin@gwdg.de
License: MIT
Keywords: nautobot,nautobot-plugin,plugin
Classifier: Development Status :: 4 - Beta
Classifier: Programming Language :: Python :: 3
Classifier: Programming Language :: Python :: 3.6
Classifier: Programming Language :: Python :: 3.7
Classifier: Programming Language :: Python :: 3.8
License-File: LICENSE
Requires-Dist: nautobot>2
